CHANGELOG.rst
LICENSE.txt
MANIFEST.in
README.rst
setup.cfg
setup.py
ari/__init__.py
ari/client.py
ari/model.py
ari.egg-info/PKG-INFO
ari.egg-info/SOURCES.txt
ari.egg-info/dependency_links.txt
ari.egg-info/requires.txt
ari.egg-info/top_level.txt