Metadata-Version: 1.1
Name: ari
Version: 0.1.1
Summary: Library for accessing the Asterisk REST Interface
Home-page: https://github.com/asterisk/asterisk_rest_libraries
Author: Digium, Inc.
Author-email: dlee@digium.com
License: BSD 3-Clause License
Platform: UNKNOWN
Classifier: Development Status :: 1 - Planning
Classifier: Intended Audience :: Developers
Classifier: Topic :: Software Development :: Libraries :: Python Modules
Classifier: License :: OSI Approved :: BSD License
Classifier: Operating System :: OS Independent
Classifier: Programming Language :: Python
